invisibleroads_macros/__init__.py
invisibleroads_macros/calculator.py
invisibleroads_macros/configuration.py
invisibleroads_macros/descriptor.py
invisibleroads_macros/disk.py
invisibleroads_macros/exceptions.py
invisibleroads_macros/geometry.py
invisibleroads_macros/html.py
invisibleroads_macros/iterable.py
invisibleroads_macros/log.py
invisibleroads_macros/security.py
invisibleroads_macros/shell.py
invisibleroads_macros/table.py
invisibleroads_macros/text.py
invisibleroads_macros/timestamp.py
invisibleroads_macros/url.py
invisibleroads_macros-0.9.5.1.dist-info/DESCRIPTION.rst
invisibleroads_macros-0.9.5.1.dist-info/METADATA
invisibleroads_macros-0.9.5.1.dist-info/RECORD
invisibleroads_macros-0.9.5.1.dist-info/WHEEL
invisibleroads_macros-0.9.5.1.dist-info/metadata.json
invisibleroads_macros-0.9.5.1.dist-info/top_level.txt
