Metadata-Version: 2.0
Name: invisibleroads-macros
Version: 0.9.5.1
Summary: Shortcut functions
Home-page: https://github.com/invisibleroads/invisibleroads-macros
Author: Roy Hyunjin Han
Author-email: rhh@crosscompute.com
License: UNKNOWN
Keywords: invisibleroads
Platform: UNKNOWN
Classifier: Programming Language :: Python
Classifier: License :: OSI Approved :: MIT License
Requires-Dist: attrs
Requires-Dist: configparser
Requires-Dist: simplejson
Requires-Dist: six
